<driver id="driver/cdj500">
  <name>cdj500</name>
  <url>http://www.ghostscript.com/</url>
  <thirdpartysupplied />
  <execution>
    <ghostscript />
    <prototype>gs -q -dBATCH -dPARANOIDSAFER -dQUIET -dNOPAUSE -dNOMEDIAATTRS -dNOINTERPOLATE -r300x300 -sDEVICE=cdj500%A%Z -sOutputFile=- -</prototype>
  </execution>
  <comments>
    <en>
      &lt;B&gt;This driver is available in the &lt;A href=&quot;https://github.com/OpenPrinting/ghostscript-printer-app&quot;&gt;Ghostscript Printer Application&lt;/A&gt;&lt;/B&gt;&lt;P&gt;
&lt;iframe src=&quot;https://snapcraft.io/ghostscript-printer-app/embedded?button=black&amp;summary=true&quot; frameborder=&quot;0&quot; width=&quot;100%&quot; height=&quot;300px&quot; style=&quot;border: 1px solid #CCC; border-radius: 2px;&quot;&gt;&lt;/iframe&gt;
    </en>
  </comments>
  <printers>
    <printer>
      <id>printer/Citizen-ProJet_IIc</id>
    </printer>
    <printer>
      <id>printer/DEC-DECwriter_520ic</id>
    </printer>
    <printer>
      <id>printer/HP-DeskJet_350C</id>
    </printer>
    <printer>
      <id>printer/HP-DeskJet_400</id>
    </printer>
    <printer>
      <id>printer/HP-DeskJet_420C</id>
    </printer>
    <printer>
      <id>printer/HP-DeskJet_500C</id>
    </printer>
    <printer>
      <id>printer/HP-DeskJet_540</id>
    </printer>
    <printer>
      <id>printer/Olivetti-JP350S</id>
    </printer>
    <printer>
      <id>printer/Olivetti-JP470</id>
    </printer>
    <printer>
      <id>printer/Xerox-DocuPrint_C11</id>
      <comments>
        <en>&quot;cdjcolor&quot; mentioned in the Notes
is actually the (Aladdin) cdj500
driver with a flag compiled in to
force to 24 bit colour in the
internal CMY map.</en>
      </comments>
    </printer>
  </printers>
</driver>
