<driver id="driver/epson">
 <name>epson</name>
 <url>http://www.cs.wisc.edu/~ghost/doc/printer.htm</url>
 <execution>
  <ghostscript />
  <prototype>gs -q -dBATCH -dPARANOIDSAFER -dQUIET -dNOPAUSE -sDEVICE=epson%A%Z -sOutputFile=- -</prototype>
 </execution>
 
 <printers>
  <printer>
   <id>printer/Generic-ESC_P_Dot_Matrix_Printer</id>
  </printer>
  <printer>
   <id>printer/Brother-MC-3000</id><!-- Brother MC-3000 -->
  </printer>
  <printer>
   <id>printer/Epson-Dot_Matrix</id><!-- Epson Dot Matrix -->
  </printer>
  <printer>
   <id>printer/Epson-L-1000</id><!-- Epson L-1000 -->
  </printer>
  <printer>
   <id>printer/Epson-LQ-500</id><!-- Epson LQ-500 -->
  </printer>
  <printer>
   <id>printer/Epson-LQ-570plus</id><!-- Epson LQ-570+ -->
   <comments>
    <en>Bound to work; someone try it out.</en>
   </comments>
  </printer>
  <printer>
   <id>printer/Epson-LX-1050</id><!-- Epson LX-1050 -->
   <comments>
    <en>Bound to work.  Someone give it a shot and report.</en>
   </comments>
  </printer>
  <printer>
   <id>printer/Okidata-ML_380</id><!-- Okidata ML 380 -->
   <comments>
    <en>printer works with the Epson dot matrix 24 pin driver</en>
   </comments>
  </printer>
  <printer>
   <id>printer/Panasonic-KX-P1123</id><!-- Panasonic KX-P1123 -->
  </printer>
  <printer>
   <id>printer/Panasonic-KX-P1124</id><!-- Panasonic KX-P1124 -->
  </printer>
  <printer>
   <id>printer/Panasonic-KX-P1624</id><!-- Panasonic KX-P1624 -->
  </printer>
  <printer>
   <id>printer/Panasonic-KX-P2023</id><!-- Panasonic KX-P2023 -->
  </printer>
  <printer>
   <id>printer/Panasonic-KX-P2123</id><!-- Panasonic KX-P2123 -->
  </printer>
  <printer>
   <id>printer/Star-LC_90</id><!-- Star LC 90 -->
  </printer>
  <printer>
   <id>printer/Star-LC24-200</id><!-- Star LC24-200 -->
  </printer>
  <printer>
   <id>printer/Star-NL-10</id><!-- Star NL-10 -->
  </printer>
  <printer>
   <id>printer/Anitech-M24</id>
  </printer>
 </printers>
</driver>