<driver id="driver/pbm2lwxl">
 <name>pbm2lwxl</name>
 <url>http://www.freelabs.com/~whitis/software/pbm2lwxl/</url>
 <execution>
  <filter />
  <prototype>gs -sDEVICE=pbm -sOutputFile=- -q -dNOPAUSE%A -dPARANOIDSAFER - -c quit | pnmflip -cw | pnmnoraw | pbm2lwxl</prototype>
 </execution>
 
 <printers>
  <printer>
   <id>printer/Avery-Personal_Label_Printer</id><!-- Avery Personal Label Printer -->
  </printer>
  <printer>
   <id>printer/Avery-Personal_Label_Printerplus</id><!-- Avery Personal Label Printer+ -->
  </printer>
  <printer>
   <id>printer/Dymo-CoStar-ASCII_250</id><!-- Dymo-CoStar ASCII 250 -->
  </printer>
  <printer>
   <id>printer/Dymo-CoStar-ASCIIplus</id><!-- Dymo-CoStar ASCII+ -->
  </printer>
  <printer>
   <id>printer/Dymo-CoStar-EL40</id><!-- Dymo-CoStar EL40 -->
  </printer>
  <printer>
   <id>printer/Dymo-CoStar-EL60</id><!-- Dymo-CoStar EL60 -->
  </printer>
  <printer>
   <id>printer/Dymo-CoStar-LabelWriter_II</id><!-- Dymo-CoStar LabelWriter II -->
  </printer>
  <printer>
   <id>printer/Dymo-CoStar-LabelWriter_XL</id><!-- Dymo-CoStar LabelWriter XL -->
  </printer>
  <printer>
   <id>printer/Dymo-CoStar-LabelWriter_XLplus</id><!-- Dymo-CoStar LabelWriter XL+ -->
  </printer>
  <printer>
   <id>printer/Dymo-CoStar-SE250</id><!-- Dymo-CoStar SE250 -->
  </printer>
  <printer>
   <id>printer/Dymo-CoStar-SE250plus</id><!-- Dymo-CoStar SE250+ -->
  </printer>
  <printer>
   <id>printer/Dymo-CoStar-Turbo</id><!-- Dymo-CoStar Turbo -->
  </printer>
 </printers>
</driver>