<printer id="printer/131424">
  <make>HP</make>
  <model>PhotoSmart P1000</model>
  <mechanism>
    <inkjet/>
    <color/>
    <resolution>
      <dpi>
        <x>2400</x>
        <y>1200</y>
      </dpi>
    </resolution>
    <consumables>
      <comments>
        <en>Refill: 1 black, 1 color cartridge</en>
      </comments>
    <!--one or more "partno" elements.--></consumables>
  </mechanism>
  <url>http://www.hp.com/cposupport/eschome.html</url>
  <lang>
    <pcl level="3"/><!--no pjl-->
    <text>
      <charset>us-ascii</charset>
    </text>
  </lang>
  <autodetect>
  <!--no known parport probe information--></autodetect>
  <functionality>A</functionality>
  <driver>hpijs-rss</driver><!--verified--><!--no "contrib_url"-->
  <comments>
    <en>

    This is essentially the same printer as the PhotoSmart 1100,
    except for the missing duplexer. It has ports on the side for
    inserting SmartMedia and CompactFlash digital &quot;film&quot; and
    has an LCD panel that lets you select pictures from the
    &quot;film&quot; to print.&lt;p&gt;

    Up/downloading of photos between the PC and the printer/memory
    card work with the &lt;a
    href=&quot;http://hpoj.sourceforge.net/&quot;&gt;HPOJ&lt;/a&gt;
    low level drivers. You need
    also the modifed USB printer.c kernel module from the &lt;a
    href=&quot;http://hpoj.sourceforge.net/&quot;&gt;HPOJ&lt;/a&gt;
    web site, if you want to access your memory cards via
    USB.&lt;p&gt;

    The best output one gets with HP&apos;s HPIJS with the patches
    from Matthias Bunte and Richard Spencer-Smith
    (&quot;hpijs-rss&quot;). The GIMP-Print driver also works (Model
    setting: &quot;pcl-900&quot;), but only up to 600 dpi.&lt;p&gt;

    </en>
  </comments>
</printer>

