<printer id="printer/59008">
  <make>Lexmark</make>
  <model>1100</model>
  <mechanism>
    <inkjet/>
    <color/>
    <resolution>
      <dpi>
        <x>600</x>
        <y>600</y>
      </dpi>
    </resolution>
    <consumables>
      <comments>
        <en>Cartridge and Printhead together. No separate Colors.</en>
      </comments>
    <!--one or more "partno" elements.--></consumables>
  </mechanism>
  <url>http://www.lexmark.com/printers/inkjet/1100/</url>
  <lang>
    <proprietary/>
  <!--no pjl--><!--No "text"?--></lang>
  <autodetect>
  <!--no known parport probe information--></autodetect>
  <functionality>D</functionality>
  <driver>lm1100</driver><!--verified--><!--no "contrib_url"-->
  <comments>
    <en>Tim Engler&apos;s driver (lm1100) now
supports 300 dpi in color and b&amp;amp;w.
The printer also no longer needs
WinDOS to switch cartridges. You
can download the necessary
software to do this from Tim
Engler&apos;s lm1100 web page. It can
print plain ASCII through gs.</en>
  </comments>
</printer>
