<printer id="printer/Canon-BJC-240">
  <make>Canon</make>
  <model>BJC-240</model>
  <mechanism>
    <inkjet/>
    <color/>
    <resolution>
      <dpi>
        <x>360</x>
        <y>360</y>
      </dpi>
    </resolution>
    <consumables>
    <!--no comments--><!--one or more "partno" elements.--></consumables>
  </mechanism><!--no "url"-->
  <lang>
    <escp/><!--no pjl-->
    <text>
      <charset>us-ascii</charset>
    </text>
  </lang>
  <autodetect>
  <!--no known parport probe information--></autodetect>
  <functionality>B</functionality>
  <driver>gutenprint</driver>
  <!--not "unverified"-->
<!--no "contrib_url"--><!--no comments!--></printer>
