<printer id="printer/Epson-E_100">
  <make>Epson</make>
  <model>E 100</model>
  <mechanism>
    <inkjet />
    <color />
    <resolution>
      <dpi>
        <x>5760</x>
        <y>1440</y>
      </dpi>
    </resolution>
  </mechanism>
  <lang>
    <escp />
    <text>
      <charset>us-ascii</charset>
    </text>
  </lang>
  <functionality>A</functionality>
  <driver>gutenprint</driver>
  <comments>
    <en>

      Japanese version of the Epson PictureMate.&lt;p&gt;

      6-color (CMYKRB), 2 pl dedicated portable photo printer with
      inkset based on R800 inks and card reader for stand-alone photo
      printing. Takes special ink cartridge and 4x6 inch (10x15 cm)
      glossy photo paper.

    </en>
  </comments>
</printer>
