<printer id="printer/Epson-Stylus_Photo_915">
  <make>Epson</make>
  <model>Stylus Photo 915</model>
  <mechanism>
    <inkjet />
    <color />
    <resolution>
      <dpi>
        <x>2880</x>
        <y>720</y>
      </dpi>
    </resolution>
  </mechanism>
  <url>http://www.epson.co.uk/product/printers/photo/styphoto895/index.htm</url>
  <lang>
    <escp />
    <text>
      <charset>us-ascii</charset>
    </text>
  </lang>
  <autodetect>
    <usb>
      <commandset>ESCPL2,BDC,D4</commandset>
      <description>EPSON Stylus Photo 915</description>
      <manufacturer>EPSON</manufacturer>
      <model>Stylus Photo 915</model>
    </usb>
  </autodetect>
  <functionality>A</functionality>
  <driver>gutenprint</driver>
  <comments>
    <en>

    This printer has a PCMCIA Type II slot to read memory cards of
    digital cameras via an appropriate PCMCIA adapter, so one can
    print photos without PC, photo download with free
    software does only work with kernel 2.4.21 or later. The memory card can be simply mounted as a
    USB-mass-storage device then.&lt;p&gt;

    6-color CMYKcm printing.&lt;p&gt;

    Roll paper feeder, USB only.&lt;p&gt;

    </en>
  </comments>
</printer>
