<printer id="printer/Epson-Stylus_Photo">
  <make>Epson</make>
  <model>Stylus Photo</model>
  <mechanism>
    <inkjet/>
    <color/>
    <resolution>
      <dpi>
        <x>720</x>
        <y>720</y>
      </dpi>
    </resolution>
    <consumables>
    <!--no comments--><!--one or more "partno" elements.--></consumables>
  </mechanism>
  <url>http://support.epson.com/hardware/printer/inkjet/pho___/index.html</url>
  <lang>
    <escp/><!--no pjl-->
    <text>
      <charset>us-ascii</charset>
    </text>
  </lang>
  <autodetect>
  <!--no known parport probe information--></autodetect>
  <functionality>A</functionality>
  <driver>gimp-print</driver><!--verified--><!--no "contrib_url"-->
  <comments>
    <en>stp now supports photo modes, alignment, etc; this printer should work perfectly.</en>
  </comments>
</printer>
