<printer id="printer/HP-LaserJet_5MP">
  <make>HP</make>
  <model>LaserJet 5MP</model>
  <mechanism>
    <laser/><!--not "color"-->
    <resolution>
      <dpi>
        <x>600</x>
        <y>600</y>
      </dpi>
    </resolution>
    <consumables>
      <comments>
        <en>Cartridge ($60-70)</en>
      </comments>
    <!--one or more "partno" elements.--></consumables>
  </mechanism>
  <url>http://www.hp.com</url>
  <lang>
    <postscript level="2">
    <!--unknown ppd filename "ppd"--></postscript>
    <pjl/>
    <text>
      <charset>us-ascii</charset>
    </text>
  </lang>
  <autodetect>
  <!--no known parport probe information--></autodetect>
  <functionality>A</functionality>
  <driver>Postscript</driver>
<!--no "contrib_url"--><!--no comments!--></printer>
