<printer id="printer/Lexmark-C510b">
  <make>Lexmark</make>
  <model>C510b</model>
  <mechanism>
    <resolution>
      <dpi>
        <x>600</x>
        <y>600</y>
      </dpi>
    </resolution>
  </mechanism>
  <lang>
    <postscript level="3" />
    <pjl />
    <text>
      <charset>us-ascii</charset>
    </text>
  </lang>
  <functionality>B</functionality>
  <driver>Postscript-Lexmark-black-only</driver>
  <drivers>
    <driver>
      <id>Postscript</id>
    </driver>
    <driver>
      <id>Postscript-Lexmark-black-only</id>
      <ppd>PPD/Lexmark/PS/Lexmark-C510b.ppd</ppd>
    </driver>
  </drivers>
  <comments>
    <en>
      For the grayscale-only model

      Throughput = 29

      Foomatic entry made by PPDtoXML T/G 0.05
      </en>
  </comments>
</printer>
