<printer id="printer/Minolta-PagePro_1400W">
  <make>Minolta</make>
  <model>PagePro 1400W</model>
  <mechanism>
    <laser />
    <resolution>
      <dpi>
        <x>1200</x>
        <y>1200</y>
      </dpi>
    </resolution>
  </mechanism>
  <url>http://www.minolta-qms.com/products/monochrome/pp1400W/index.asp</url>
  <lang>
    <proprietary />
  </lang>
  <autodetect>
    <usb>
      <commandset>NA</commandset>
      <description>KONICA MINOLTA PP1400W</description>
      <manufacturer>KONICA MINOLTA</manufacturer>
      <model>PP1400W</model>
    </usb>
  </autodetect>
  <functionality>B</functionality>
  <driver>min12xxw</driver>
  <comments>
    <en>
     Low cost laser.
    </en>
  </comments>
</printer>
