<printer id="printer/Oce-8445PS">
  <make>Oce</make>
  <model>8445</model>
  <mechanism>
    <laser />
    <resolution>
      <dpi>
        <x>600</x>
        <y>600</y>
      </dpi>
    </resolution>
  </mechanism>
  <url>http://www.oce.com</url>
  <lang>
    <postscript level="3" />
    <pcl level="5" />
    <pjl />
    <text>
      <charset>us-ascii</charset>
    </text>
  </lang>
  <autodetect>
    <general>
      <ieee1284>MFG:Oce;MDL:Oce 8445;</ieee1284>
      <manufacturer>Oce</manufacturer>
      <model>Oce 8445</model>
    </general>
  </autodetect>
  <functionality>A</functionality>
  <driver>Postscript-Oce</driver>
  <drivers>
    <driver>
      <id>ljet3</id>
    </driver>
    <driver>
      <id>ljet3d</id>
    </driver>
    <driver>
      <id>Postscript</id>
    </driver>
    <driver>
      <id>Postscript-Oce</id>
      <ppd>PPD/Oce/Oce-8445PS/1/OC8445_3.ppd</ppd>
    </driver>
    <driver>
      <id>Postscript2-Oce</id>
      <ppd>PPD/Oce/Others/OC8445_2.ppd</ppd>
    </driver>
  </drivers>
  <comments>
    <en>

      &lt;p&gt;

      Maximum paper width: 11.7 inches / 29.7 cm
      (Wide format printer)&lt;p&gt;

      Printing engine speed: 45 pages/min&lt;p&gt;&lt;p&gt;

      Consumables/Refills: Toner
      &lt;p&gt;


    </en>
  </comments>
</printer>
