<printer id="printer/QMS-ps-810">
  <make>QMS</make>
  <model>ps-810</model>
  <mechanism>
    <laser/><!--not "color"-->
    <resolution>
      <dpi>
        <x>300</x>
        <y>300</y>
      </dpi>
    </resolution>
    <consumables>
      <comments>
        <en>Canon EP-S</en>
      </comments>
    <!--one or more "partno" elements.--></consumables>
  </mechanism><!--no "url"-->
  <lang>
    <postscript level="1">
    <!--unknown ppd filename "ppd"--></postscript>
  <!--no pjl--><!--No "text"?--></lang>
  <autodetect>
  <!--no known parport probe information--></autodetect>
  <functionality>B</functionality>
  <driver>Postscript</driver>
  <unverified/><!--no "contrib_url"-->
  <comments>
    <en>Very old (circa &apos;89), reliable printer.
Laserwriter clone.
Native postscript level 1.
apsfilter handles ascii etc.
print from netscape works.
print from acrobat reader does not,
even w/level 1 set.</en>
  </comments>
</printer>
