<printer id="printer/Sharp-AR-C261FPPS">
   <make>Sharp</make>
   <model>AR-C261FPPS</model>
   <mechanism>
   <color/>
      <led/>
      <resolution>
         <dpi>
            <!--x unknown-->
            <!--y unknown-->
         </dpi>
      <consumables></consumables>
      </resolution>
   </mechanism>
   <url></url>
   <lang>
      <postscript level="3" />
      <!--no pjl-->
      <!--no "text"-->
   </lang>
   <functionality>B</functionality>
   <driver>Postscript</driver>
  <drivers>
    <driver>
      <id>Postscript</id>
      <ppd>PPD/Sharp/sc261fpj.ppd</ppd>
    </driver>
  </drivers>
   <comments>
      <en>
      Throughput = 26

      Foomatic entry made by PPDtoXML T/G 0.06
      </en>
   </comments>
</printer>
